setup.py
mecv/__init__.py
mecv.egg-info/PKG-INFO
mecv.egg-info/SOURCES.txt
mecv.egg-info/dependency_links.txt
mecv.egg-info/requires.txt
mecv.egg-info/top_level.txt