Metadata-Version: 1.2
Name: mecv
Version: 0.0.1
Summary: A Modular and Extensible Framework for Computer Vision
Home-page: https://github.com/mtli/mecv
Author: Mengtian (Martin) Li
Author-email: martinli.work@gmail.com
License: MIT
Keywords: computer vision deep learning pytorch
Platform: UNKNOWN
Classifier: Development Status :: 4 - Beta
Classifier: Intended Audience :: Science/Research
Classifier: Topic :: Scientific/Engineering :: Artificial Intelligence
Classifier: License :: OSI Approved :: MIT License
Classifier: Programming Language :: Python :: 3
Requires-Python: >=3
